{"paragraphs":[{"text":"%sql\nCREATE TEMPORARY VIEW rsvps\nUSING org.apache.spark.sql.parquet\nOPTIONS (\n  path \"s3a://tristan-meetup-data/rsvps/2017-05-11-03-38-29\"\n)","dateUpdated":"2017-05-11T04:13:59+0000","config":{"tableHide":false,"editorSetting":{"language":"sql","editOnDblClick":false},"colWidth":12,"editorMode":"ace/mode/sql","results":{"0":{"graph":{"mode":"table","height":300,"optionOpen":false},"helium":{}}},"enabled":true},"settings":{"params":{},"forms":{}},"results":{"code":"SUCCESS","msg":[{"type":"TABLE","data":""}]},"apps":[],"jobName":"paragraph_1494473738503_-111696621","id":"20170501-041721_1402468808","dateCreated":"2017-05-11T03:35:38+0000","status":"FINISHED","progressUpdateIntervalMs":500,"focus":true,"$$hashKey":"object:7048","user":"anonymous","dateFinished":"2017-05-11T04:13:51+0000","dateStarted":"2017-05-11T04:13:51+0000"},{"text":"%sql\nCREATE TEMPORARY VIEW events\nUSING org.apache.spark.sql.parquet\nOPTIONS (\n  path \"s3a://tristan-meetup-data/events/2017-05-11-03-38-29\"\n)","dateUpdated":"2017-05-11T04:14:09+0000","config":{"tableHide":false,"editorSetting":{"language":"sql","editOnDblClick":false},"colWidth":12,"editorMode":"ace/mode/sql","results":{},"enabled":true},"settings":{"params":{},"forms":{}},"results":{"code":"SUCCESS","msg":[{"type":"TABLE","data":""}]},"apps":[],"jobName":"paragraph_1494473738504_-113620365","id":"20170501-041805_1747708348","dateCreated":"2017-05-11T03:35:38+0000","status":"FINISHED","progressUpdateIntervalMs":500,"$$hashKey":"object:7049","user":"anonymous","dateFinished":"2017-05-11T04:14:10+0000","dateStarted":"2017-05-11T04:14:09+0000"},{"text":"%sql\nCREATE TEMPORARY VIEW venues\nUSING org.apache.spark.sql.parquet\nOPTIONS (\n  path \"s3a://tristan-meetup-data/venues/2017-05-11-03-38-29\"\n)","dateUpdated":"2017-05-11T04:14:15+0000","config":{"tableHide":false,"editorSetting":{"language":"sql","editOnDblClick":false},"colWidth":12,"editorMode":"ace/mode/sql","results":{},"enabled":true},"settings":{"params":{},"forms":{}},"results":{"code":"SUCCESS","msg":[{"type":"TABLE","data":""}]},"apps":[],"jobName":"paragraph_1494473738505_-114005114","id":"20170501-041830_1866962610","dateCreated":"2017-05-11T03:35:38+0000","status":"FINISHED","progressUpdateIntervalMs":500,"$$hashKey":"object:7050","user":"anonymous","dateFinished":"2017-05-11T04:14:16+0000","dateStarted":"2017-05-11T04:14:15+0000"},{"text":"%sql\nCREATE TEMPORARY VIEW groups\nUSING org.apache.spark.sql.parquet\nOPTIONS (\n  path \"s3a://tristan-meetup-data/groups/2017-05-11-03-38-29\"\n)","dateUpdated":"2017-05-11T04:14:20+0000","config":{"tableHide":false,"editorSetting":{"language":"sql","editOnDblClick":false},"colWidth":12,"editorMode":"ace/mode/sql","results":{},"enabled":true},"settings":{"params":{},"forms":{}},"results":{"code":"SUCCESS","msg":[{"type":"TABLE","data":""}]},"apps":[],"jobName":"paragraph_1494473738505_-114005114","id":"20170501-041849_77023250","dateCreated":"2017-05-11T03:35:38+0000","status":"FINISHED","progressUpdateIntervalMs":500,"$$hashKey":"object:7051","user":"anonymous","dateFinished":"2017-05-11T04:14:21+0000","dateStarted":"2017-05-11T04:14:20+0000"},{"text":"%sql\nCREATE TEMPORARY VIEW groups_topics\nUSING org.apache.spark.sql.parquet\nOPTIONS (\n  path \"s3a://tristan-meetup-data/groups_topics/2017-05-11-03-38-29\"\n)","dateUpdated":"2017-05-11T04:14:26+0000","config":{"tableHide":false,"editorSetting":{"language":"sql","editOnDblClick":false},"colWidth":12,"editorMode":"ace/mode/sql","results":{},"enabled":true},"settings":{"params":{},"forms":{}},"results":{"code":"SUCCESS","msg":[{"type":"TABLE","data":""}]},"apps":[],"jobName":"paragraph_1494473738506_-112850868","id":"20170501-042319_1609777938","dateCreated":"2017-05-11T03:35:38+0000","status":"FINISHED","progressUpdateIntervalMs":500,"$$hashKey":"object:7052","user":"anonymous","dateFinished":"2017-05-11T04:14:27+0000","dateStarted":"2017-05-11T04:14:26+0000"},{"text":"%sql\nCREATE TEMPORARY VIEW members\nUSING org.apache.spark.sql.parquet\nOPTIONS (\n  path \"s3a://tristan-meetup-data/members/2017-05-11-03-38-29\"\n)","dateUpdated":"2017-05-11T04:14:31+0000","config":{"tableHide":false,"editorSetting":{"language":"sql","editOnDblClick":false},"colWidth":12,"editorMode":"ace/mode/sql","results":{},"enabled":true},"settings":{"params":{},"forms":{}},"results":{"code":"SUCCESS","msg":[{"type":"TABLE","data":""}]},"apps":[],"jobName":"paragraph_1494473738506_-112850868","id":"20170501-042344_1668137268","dateCreated":"2017-05-11T03:35:38+0000","status":"FINISHED","progressUpdateIntervalMs":500,"$$hashKey":"object:7053","user":"anonymous","dateFinished":"2017-05-11T04:14:32+0000","dateStarted":"2017-05-11T04:14:31+0000"},{"text":"%sql\nCREATE TEMPORARY VIEW topics\nUSING org.apache.spark.sql.parquet\nOPTIONS (\n  path \"s3a://tristan-meetup-data/topics/2017-05-11-03-38-29\"\n)","dateUpdated":"2017-05-11T04:14:41+0000","config":{"tableHide":false,"editorSetting":{"language":"sql","editOnDblClick":false},"colWidth":12,"editorMode":"ace/mode/sql","results":{"0":{"graph":{"mode":"table","height":300,"optionOpen":false},"helium":{}}},"enabled":true},"settings":{"params":{},"forms":{}},"results":{"code":"SUCCESS","msg":[{"type":"TABLE","data":""}]},"apps":[],"jobName":"paragraph_1494473738507_-113235616","id":"20170501-042429_1978894155","dateCreated":"2017-05-11T03:35:38+0000","status":"FINISHED","progressUpdateIntervalMs":500,"$$hashKey":"object:7054","user":"anonymous","dateFinished":"2017-05-11T04:14:41+0000","dateStarted":"2017-05-11T04:14:41+0000"},{"text":"%sql\n-- find the most active member\nSELECT members.member_id, members.member_name, count(rsvps.rsvp_id) as num_rsvp FROM members JOIN rsvps ON rsvps.member_id = members.member_id GROUP BY members.member_id, members.member_name ORDER BY num_rsvp DESC LIMIT 20","dateUpdated":"2017-05-11T04:14:49+0000","config":{"tableHide":false,"editorSetting":{"language":"sql","editOnDblClick":false},"colWidth":12,"editorMode":"ace/mode/sql","results":{"0":{"graph":{"mode":"table","height":300,"optionOpen":false},"helium":{}}},"enabled":true},"settings":{"params":{},"forms":{}},"results":{"code":"SUCCESS","msg":[{"type":"TABLE","data":"member_id\tmember_name\tnum_rsvp\n5520020\tMichael\t15239\n188713501\tWolfram Zumm\t10844\n142142252\tHenry\t8046\n220206640\tRobot1\t7985\n82617992\tGlobal Organiser - Raj Dan\t5850\n217212775\tHelen Kim\t5350\n8837208\tLouis\t5274\n8071543\tDavid\t4860\n2531721\tAntwone\t4296\n141737452\tJohann\t3682\n20914241\tDung\t3250\n8250723\tJoel.E5\t2794\n8516444\tRory\t2541\n220212469\tRobot4\t2219\n220219495\tRobot25\t2145\n1874482\tJVM\t2128\n55243872\tChristophe\t1935\n183252066\tKentaroh Imagawa\t1911\n9750821\tHammad Soomro\t1853\n205900159\t@neohack22\t1596\n"}]},"apps":[],"jobName":"paragraph_1494473738507_-113235616","id":"20170501-042527_735519841","dateCreated":"2017-05-11T03:35:38+0000","status":"FINISHED","progressUpdateIntervalMs":500,"$$hashKey":"object:7055","user":"anonymous","dateFinished":"2017-05-11T04:15:20+0000","dateStarted":"2017-05-11T04:14:49+0000"},{"text":"%sql\n-- find the most popular group (people answer 'rsvp = yes')\nSELECT groups.group_id, groups.group_name, groups.group_urlname, count(rsvps.rsvp_id) as rsvp_yes FROM groups JOIN rsvps ON groups.group_id = rsvps.group_id WHERE rsvps.response = 'yes' GROUP BY groups.group_id, groups.group_name, groups.group_urlname ORDER BY rsvp_yes DESC LIMIT 20","dateUpdated":"2017-05-11T04:15:51+0000","config":{"tableHide":false,"editorSetting":{"language":"sql","editOnDblClick":false},"colWidth":12,"editorMode":"ace/mode/sql","results":{},"enabled":true},"settings":{"params":{},"forms":{}},"results":{"code":"SUCCESS","msg":[{"type":"TABLE","data":"group_id\tgroup_name\tgroup_urlname\trsvp_yes\n21977811\tAutomation One\tAutomation-One\t10750\n18297604\t\"I wanted to do that . . .  . . . .Just not alone!!\"\tIWantToDoThat\t5334\n1576378\tIt's Boomertime!\tboomertime\t2773\n3332802\tSunrise to Sunset Hikers\tSunrise-to-Sunset-Hikers\t2313\n21979560\tAutomation-25\tAutomation-25\t2142\n3193052\tCelebrate Atlanta\tCelebrate-Atlanta\t1996\n18301612\tIF7sports juega aquí Fútbol 7\tif7sports\t1915\n1338658\tHudson Valley Hikers\thvhikers\t1858\n274386\tLondon On Board\tLondonOnBoard\t1849\n13402242\tDocker Online Meetup\tDocker-Online-Meetup\t1802\n18385615\tBarcelona International Meeting\tBarcelona-International-Meeting\t1788\n1766167\tJames River Hikers\tJames-River-Hikers\t1770\n2431562\tSlow and Steady Hikers\tSlow-and-Steady-Hikers\t1722\n19294414\tTensorFlow Tel-Aviv\tTensorFlow-Tel-Aviv\t1686\n216740\tVegasHikers\tVegasHikers\t1652\n20455357\tStudenckie Grupy .NET\tStudenckie-Grupy-NET\t1525\n2622372\tI'm Not Dead Yet --- 50+ Meetup\tIm-Not-Dead-Yet-50-plus\t1521\n1961331\tSydney Explorers\tSydney-Explorers\t1482\n3460952\tLong Island Adult Soccer\tLongIslandSoccer\t1473\n3386582\tCascade Free Group Rides\tcascaderides\t1360\n"}]},"apps":[],"jobName":"paragraph_1494473738508_-115159361","id":"20170501-043646_1433324963","dateCreated":"2017-05-11T03:35:38+0000","status":"FINISHED","progressUpdateIntervalMs":500,"$$hashKey":"object:7056","user":"anonymous","dateFinished":"2017-05-11T04:16:18+0000","dateStarted":"2017-05-11T04:15:51+0000"},{"text":"%sql\n","dateUpdated":"2017-05-11T03:35:38+0000","config":{"colWidth":12,"editorMode":"ace/mode/sql","results":{},"enabled":true,"editorSetting":{"language":"sql","editOnDblClick":false}},"settings":{"params":{},"forms":{}},"apps":[],"jobName":"paragraph_1494473738508_-115159361","id":"20170501-051446_465941933","dateCreated":"2017-05-11T03:35:38+0000","status":"READY","errorMessage":"","progressUpdateIntervalMs":500,"$$hashKey":"object:7057"}],"name":"EDA","id":"2CFAVGA91","angularObjects":{"2BRWU4WXC:shared_process":[],"2AM1YV5CU:shared_process":[],"2AJXGMUUJ:shared_process":[],"2ANGGHHMQ:shared_process":[],"2AKK3QQXU:shared_process":[]},"config":{"looknfeel":"default","personalizedMode":"false"},"info":{}}